[
    {
        "name": "Hypnocatrice Training",
        "time-limit": 50,
        "location": "GrtForest(Day)",
        "main-monsters": "Hypnocatrice",
        "goal-condition": "Hunt the Hypnocatrice",
        "quest-details": "Considering all the monsters you've hunted up to this point, this exercise should be nothing! Off you go!",
        "difficulty": 1,
        "point-multiplier": 100,
        "weapon": {
            "name": "Black Doom Flame",
            "decorations": []
        },
        "armors": [
            {
                "name": "Kut-Ku Helm U",
                "decorations": [
                    {
                        "name": "Celebrity Jewel"
                    }
                ]
            },
            {
                "name": "Kut-Ku Mail U",
                "decorations": [
                    {
                        "name": "Expert Jewel"
                    }
                ]
            },
            {
                "name": "Kut-Ku Vambraces U",
                "decorations": [
                    {
                        "name": "Strength Jewel"
                    }
                ]
            },
            {
                "name": "Kut-Ku Tasset U",
                "decorations": [
                    {
                        "name": "Strength Jewel"
                    }
                ]
            },
            {
                "name": "Kut-Ku Greaves U",
                "decorations": []
            }
        ],
        "items": [
            {
                "name": "Whetstone",
                "count": 3
            },
            {
                "name": "Mega Potion",
                "count": 5
            },
            {
                "name": "Ration",
                "count": 4
            },
            {
                "name": "Sply Pitfall Trp",
                "count": 1
            }
        ]
    },
    {
        "name": "Hypnocatrice Training",
        "time-limit": 50,
        "location": "GrtForest(Day)",
        "main-monsters": "Hypnocatrice",
        "goal-condition": "Hunt the Hypnocatrice",
        "quest-details": "Behold this invincible Hypnocatrice! So what should you do? Create a weak spot, of course! Aim for its legs and bring it down!",
        "difficulty": 1,
        "point-multiplier": 90,
        "weapon": {
            "name": "Monoblos Scythe+",
            "decorations": []
        },
        "armors": [
            {
                "name": "Piercing of Fate",
                "decorations": []
            },
            {
                "name": "Hunter's Mail S",
                "decorations": [
                    {
                        "name": "Attack Jewel"
                    }
                ]
            },
            {
                "name": "Hunter's Vambraces S",
                "decorations": [
                    {
                        "name": "Attack Jewel"
                    }
                ]
            },
            {
                "name": "Hunter's Tasset S",
                "decorations": [
                    {
                        "name": "SpeedyRecvrJewel"
                    }
                ]
            },
            {
                "name": "Hunter's Greaves S",
                "decorations": []
            }
        ],
        "items": [
            {
                "name": "Whetstone",
                "count": 3
            },
            {
                "name": "Mega Potion",
                "count": 5
            },
            {
                "name": "Ration",
                "count": 4
            },
            {
                "name": "Psychoserum",
                "count": 1
            }
        ]
    },
    {
        "name": "Hypnocatrice Training",
        "time-limit": 50,
        "location": "GrtForest(Day)",
        "main-monsters": "Hypnocatrice",
        "goal-condition": "Hunt the Hypnocatrice",
        "quest-details": "It's everybody's favorite: Hunting Horn Lessons! Give Purple-Purple-Red-Red-Yellow a bellow! And as always, use it twice!",
        "difficulty": 1,
        "point-multiplier": 95,
        "weapon": {
            "name": "Wolf Shamisen",
            "decorations": []
        },
        "armors": [
            {
                "name": "Vespoid Helm U",
                "decorations": []
            },
            {
                "name": "Vespoid Mail U",
                "decorations": []
            },
            {
                "name": "Vespoid Vambraces U",
                "decorations": []
            },
            {
                "name": "Vespoid Tasset U",
                "decorations": []
            },
            {
                "name": "Vespoid Greaves U",
                "decorations": []
            }
        ],
        "items": [
            {
                "name": "Whetstone",
                "count": 3
            },
            {
                "name": "Mega Potion",
                "count": 5
            },
            {
                "name": "Ration",
                "count": 4
            },
            {
                "name": "Supply Flash Bmb",
                "count": 1
            }
        ]
    },
    {
        "name": "Hypnocatrice Training",
        "time-limit": 50,
        "location": "GrtForest(Day)",
        "main-monsters": "Hypnocatrice",
        "goal-condition": "Hunt the Hypnocatrice",
        "quest-details": "You can't guard against Sleep Breath! Dodge when you have to and attack when you can. Being aware of your position is everything!",
        "difficulty": 1,
        "point-multiplier": 105,
        "weapon": {
            "name": "Scissor Cannon",
            "decorations": []
        },
        "armors": [
            {
                "name": "Hi-Metal Helm S",
                "decorations": []
            },
            {
                "name": "Hermitaur Mail S",
                "decorations": []
            },
            {
                "name": "Hi-Metal Vambraces S",
                "decorations": []
            },
            {
                "name": "Hermitaur Tasset S",
                "decorations": []
            },
            {
                "name": "Hi-Metal Greaves S",
                "decorations": []
            }
        ],
        "items": [
            {
                "name": "Whetstone",
                "count": 3
            },
            {
                "name": "Mega Potion",
                "count": 5
            },
            {
                "name": "Ration",
                "count": 4
            },
            {
                "name": "Shock Trap",
                "count": 1
            }
        ]
    },
    {
        "name": "Hypnocatrice Training",
        "time-limit": 50,
        "location": "GrtForest(Day)",
        "main-monsters": "Hypnocatrice",
        "goal-condition": "Hunt the Hypnocatrice",
        "quest-details": "Hunting with a bow! The best way to reach out and nail a beast from a great distance! Just be wray of its kicks! Yeowch!",
        "difficulty": 1,
        "point-multiplier": 100,
        "weapon": {
            "name": "Hunter's PowerBowIII",
            "decorations": []
        },
        "armors": [
            {
                "name": "Yellow Piercing",
                "decorations": []
            },
            {
                "name": "Gypceros Vest S",
                "decorations": []
            },
            {
                "name": "Plesioth Guards S",
                "decorations": []
            },
            {
                "name": "Gypceros Coat S",
                "decorations": []
            },
            {
                "name": "Gypceros Leggings S",
                "decorations": []
            }
        ],
        "items": [
            {
                "name": "Power Coating",
                "count": 30
            },
            {
                "name": "Poison Coating",
                "count": 10
            },
            {
                "name": "Mega Potion",
                "count": 5
            },
            {
                "name": "Ration",
                "count": 4
            },
            {
                "name": "Supply Flash Bmb",
                "count": 1
            }
        ]
    },
    {
        "name": "Emerald Congalala Training",
        "time-limit": 50,
        "location": "Old Jungle",
        "main-monsters": "Emerald Congalala",
        "goal-condition": "Hunt the Emerald Congalala",
        "quest-details": "This armor is resistant to smells! You'll stay lemon-fresh no matter what! But it's not invincible, so good luck dodging!",
        "difficulty": 2,
        "point-multiplier": 95,
        "weapon": {
            "name": "Icicle Daggers",
            "decorations": []
        },
        "armors": [
            {
                "name": "Conga Helm S",
                "decorations": []
            },
            {
                "name": "Conga Mail S",
                "decorations": []
            },
            {
                "name": "Conga Vambraces S",
                "decorations": []
            },
            {
                "name": "Conga Tasset S",
                "decorations": []
            },
            {
                "name": "Conga Greaves S",
                "decorations": []
            }
        ],
        "items": [
            {
                "name": "Whetstone",
                "count": 3
            },
            {
                "name": "Mega Potion",
                "count": 5
            },
            {
                "name": "Ration",
                "count": 2
            },
            {
                "name": "Power Juice",
                "count": 1
            },
            {
                "name": "Shock Trap",
                "count": 1
            },
            {
                "name": "Tainted Meat",
                "count": 1
            }
        ]
    },
    {
        "name": "Emerald Congalala Training",
        "time-limit": 50,
        "location": "Old Jungle",
        "main-monsters": "Emerald Congalala",
        "goal-condition": "Hunt the Emerald Congalala",
        "quest-details": "Get the ol' Trap Master skill on I see! That ensures a 100% combination success rate! Materials? Still got to get those yourself!",
        "difficulty": 2,
        "point-multiplier": 105,
        "weapon": {
            "name": "Enforcer's Axe",
            "decorations": []
        },
        "armors": [
            {
                "name": "Battle Helm S",
                "decorations": [
                    {
                        "name": "TrapMasterJewel"
                    }
                ]
            },
            {
                "name": "Battle Mail S",
                "decorations": [
                    {
                        "name": "TrapMasterJewel"
                    }
                ]
            },
            {
                "name": "Battle Vambraces S",
                "decorations": [
                    {
                        "name": "TrapMasterJewel"
                    }
                ]
            },
            {
                "name": "Battle Tasset S",
                "decorations": [
                    {
                        "name": "TrapMasterJewel"
                    }
                ]
            },
            {
                "name": "Battle Greaves S",
                "decorations": [
                    {
                        "name": "TrapMasterJewel"
                    }
                ]
            }
        ],
        "items": [
            {
                "name": "Whetstone",
                "count": 3
            },
            {
                "name": "Mega Potion",
                "count": 5
            },
            {
                "name": "Ration",
                "count": 4
            },
            {
                "name": "Paintball",
                "count": 2
            },
            {
                "name": "Toadstool",
                "count": 1
            },
            {
                "name": "Sleep Herb",
                "count": 1
            },
            {
                "name": "Iron Pickaxe",
                "count": 1
            },
            {
                "name": "Deodorant",
                "count": 4
            }
        ]
    },
    {
        "name": "Emerald Congalala Training",
        "time-limit": 50,
        "location": "Old Jungle",
        "main-monsters": "Emerald Congalala",
        "goal-condition": "Hunt the Emerald Congalala",
        "quest-details": "It may be powerful, but so are you! This is going to be a match of strength! Go for its head and show it what you've got!",
        "difficulty": 2,
        "point-multiplier": 100,
        "weapon": {
            "name": "Onslaught Hammer",
            "decorations": []
        },
        "armors": [
            {
                "name": "Piercing of Might",
                "decorations": []
            },
            {
                "name": "Hypno Mail S",
                "decorations": [
                    {
                        "name": "Marathon Jewel"
                    }
                ]
            },
            {
                "name": "Gypceros Vambraces S",
                "decorations": [
                    {
                        "name": "Marathon Jewel"
                    }
                ]
            },
            {
                "name": "Hypno Tasset S",
                "decorations": []
            },
            {
                "name": "Hypno Greaves S",
                "decorations": []
            }
        ],
        "items": [
            {
                "name": "Whetstone",
                "count": 3
            },
            {
                "name": "Mega Potion",
                "count": 5
            },
            {
                "name": "Ration",
                "count": 6
            },
            {
                "name": "Deodorant",
                "count": 3
            }
        ]
    },
    {
        "name": "Emerald Congalala Training",
        "time-limit": 50,
        "location": "Old Jungle",
        "main-monsters": "Emerald Congalala",
        "goal-condition": "Hunt the Emerald Congalala",
        "quest-details": "Usually, even if you guard, the smell lingers on. But no need to worry with this! Guard well and then counterattack away!",
        "difficulty": 2,
        "point-multiplier": 105,
        "weapon": {
            "name": "Frost Icicle",
            "decorations": []
        },
        "armors": [
            {
                "name": "Hermitaur Helm U",
                "decorations": []
            },
            {
                "name": "Hermitaur Mail U",
                "decorations": []
            },
            {
                "name": "Hermitaur Braces U",
                "decorations": []
            },
            {
                "name": "Hermitaur Tasset U",
                "decorations": []
            },
            {
                "name": "Hermitaur Greaves U",
                "decorations": []
            }
        ],
        "items": [
            {
                "name": "Whetstone",
                "count": 3
            },
            {
                "name": "Mega Potion",
                "count": 5
            },
            {
                "name": "Ration",
                "count": 4
            },
            {
                "name": "Tainted Meat",
                "count": 2
            },
            {
                "name": "Paralyze Thr Knf",
                "count": 4
            },
            {
                "name": "Deodorant",
                "count": 2
            }
        ]
    },
    {
        "name": "Emerald Congalala Training",
        "time-limit": 50,
        "location": "Old Jungle",
        "main-monsters": "Emerald Congalala",
        "goal-condition": "Hunt the Emerald Congalala",
        "quest-details": "Attacking those things it lobs with its tail isn't going to get you very far. Dodge, then attack. One false step and ...",
        "difficulty": 2,
        "point-multiplier": 95,
        "weapon": {
            "name": "Quickcaster+",
            "decorations": []
        },
        "armors": [
            {
                "name": "Conga Cap U",
                "decorations": [
                    {
                        "name": "No Food Jewel"
                    }
                ]
            },
            {
                "name": "Conga Vest U",
                "decorations": []
            },
            {
                "name": "Conga Guards U",
                "decorations": []
            },
            {
                "name": "Conga Coat U",
                "decorations": []
            },
            {
                "name": "Conga Leggings U",
                "decorations": []
            }
        ],
        "items": [
            {
                "name": "Normal S Lv1",
                "count": "Infinity"
            },
            {
                "name": "Normal S Lv2",
                "count": 50
            },
            {
                "name": "Pierce S Lv2",
                "count": 40
            },
            {
                "name": "Pellet S Lv2",
                "count": 30
            },
            {
                "name": "Freeze S",
                "count": 40
            },
            {
                "name": "Sleep S Lv2",
                "count": 8
            },
            {
                "name": "Mega Potion",
                "count": 5
            },
            {
                "name": "Ration",
                "count": 4
            },
            {
                "name": "Drugged Meat",
                "count": 1
            },
            {
                "name": "Sply Lg Brrl Bmb",
                "count": 2
            },
            {
                "name": "Deodorant",
                "count": 3
            }
        ]
    },
    {
        "name": "Plum D. Hermitaur Training",
        "time-limit": 50,
        "location": "Old Desert",
        "main-monsters": "Plum D. Hermitaur",
        "goal-condition": "Hunt the Plum D. Hermitaur",
        "quest-details": "Juggling bombs and a sword... Pretty hot stuff if you ask me. Better to stick to one or risk embarrassing yourself royally!",
        "difficulty": 2,
        "point-multiplier": 95,
        "weapon": {
            "name": "Expert Sword",
            "decorations": []
        },
        "armors": [
            {
                "name": "Genprey Helm S",
                "decorations": [
                    {
                        "name": "Bombardier Jewel"
                    }
                ]
            },
            {
                "name": "Genprey Mail S",
                "decorations": [
                    {
                        "name": "Bombardier Jewel"
                    }
                ]
            },
            {
                "name": "Genprey Vambraces S",
                "decorations": [
                    {
                        "name": "Bombardier Jewel"
                    }
                ]
            },
            {
                "name": "Genprey Tasset S",
                "decorations": [
                    {
                        "name": "Bombardier Jewel"
                    }
                ]
            },
            {
                "name": "Genprey Greaves S",
                "decorations": [
                    {
                        "name": "Bombardier Jewel"
                    }
                ]
            }
        ],
        "items": [
            {
                "name": "Whetstone",
                "count": 3
            },
            {
                "name": "Mega Potion",
                "count": 5
            },
            {
                "name": "Ration",
                "count": 4
            },
            {
                "name": "Cool Drink",
                "count": 3
            },
            {
                "name": "Paintball",
                "count": 2
            },
            {
                "name": "Sply Lg Brrl Bmb",
                "count": 2
            },
            {
                "name": "Lg Barrel-Bomb",
                "count": 2
            },
            {
                "name": "Sm Barrel-Bomb",
                "count": 3
            }
        ]
    },
    {
        "name": "Plum D. Hermitaur Training",
        "time-limit": 50,
        "location": "Old Desert",
        "main-monsters": "Plum D. Hermitaur",
        "goal-condition": "Hunt the Plum D. Hermitaur",
        "quest-details": "Ha ha! Too much stuff can get in your way, so here, let me take some of it off your hands! Thanks.. Hey, what's that face for?",
        "difficulty": 2,
        "point-multiplier": 100,
        "weapon": {
            "name": "True Dragon's Jaw",
            "decorations": []
        },
        "armors": [
            {
                "name": "Cephalos Helm U",
                "decorations": []
            },
            {
                "name": "Cephalos Mail U",
                "decorations": []
            },
            {
                "name": "Cephalos Vambraces U",
                "decorations": []
            },
            {
                "name": "Cephalos Tasset U",
                "decorations": []
            },
            {
                "name": "Cephalos Greaves U",
                "decorations": []
            }
        ],
        "items": [
            {
                "name": "Whetstone",
                "count": 4
            },
            {
                "name": "Mega Potion",
                "count": 5
            }
        ]
    },
    {
        "name": "Plum D. Hermitaur Training",
        "time-limit": 50,
        "location": "Old Desert",
        "main-monsters": "Plum D. Hermitaur",
        "goal-condition": "Hunt the Plum D. Hermitaur",
        "quest-details": "Three Yellows make supersonic waves, so remem... huh? The usual? Purple-Purple-Green-Green-Yellow-Purple-Yellow, OK!?",
        "difficulty": 2,
        "point-multiplier": 95,
        "weapon": {
            "name": "Velociprey Balloon",
            "decorations": []
        },
        "armors": [
            {
                "name": "Bone Helm S",
                "decorations": []
            },
            {
                "name": "Bone Mail S",
                "decorations": []
            },
            {
                "name": "Bone Vambraces S",
                "decorations": []
            },
            {
                "name": "Bone Tasset S",
                "decorations": []
            },
            {
                "name": "Bone Greaves S",
                "decorations": [
                    {
                        "name": "Map Jewel"
                    }
                ]
            }
        ],
        "items": [
            {
                "name": "Whetstone",
                "count": 3
            },
            {
                "name": "Mega Potion",
                "count": 5
            },
            {
                "name": "Ration",
                "count": 4
            },
            {
                "name": "Cool Drink",
                "count": 3
            },
            {
                "name": "Power Seed",
                "count": 2
            }
        ]
    },
    {
        "name": "Plum D. Hermitaur Training",
        "time-limit": 50,
        "location": "Old Desert",
        "main-monsters": "Plum D. Hermitaur",
        "goal-condition": "Hunt the Plum D. Hermitaur",
        "quest-details": "\"Clash of the Titans, Part 2!\" is what I'd say if going head-on wasn't going to get you squashed. Go get it from the side!",
        "difficulty": 2,
        "point-multiplier": 105,
        "weapon": {
            "name": "Ceanataur Piercer",
            "decorations": []
        },
        "armors": [
            {
                "name": "Black Belt Helm S",
                "decorations": []
            },
            {
                "name": "Narga Mail S",
                "decorations": [
                    {
                        "name": "Attack Jewel"
                    }
                ]
            },
            {
                "name": "BlackBeltVambraces S",
                "decorations": []
            },
            {
                "name": "Chrome Metal Coat",
                "decorations": []
            },
            {
                "name": "Narga Greaves S",
                "decorations": [
                    {
                        "name": "Jumping Jewel"
                    }
                ]
            }
        ],
        "items": [
            {
                "name": "Whetstone",
                "count": 3
            },
            {
                "name": "Mega Potion",
                "count": 5
            },
            {
                "name": "Ration",
                "count": 4
            },
            {
                "name": "Cool Drink",
                "count": 3
            },
            {
                "name": "Sonic Bomb",
                "count": 2
            }
        ]
    },
    {
        "name": "Plum D. Hermitaur Training",
        "time-limit": 50,
        "location": "Old Desert",
        "main-monsters": "Plum D. Hermitaur",
        "goal-condition": "Hunt the Plum D. Hermitaur",
        "quest-details": "When it's mad, stay the heck away, the farther the better, unless you want to be Breathed or Pressed to kingdom come!",
        "difficulty": 2,
        "point-multiplier": 90,
        "weapon": {
            "name": "Tail Catapult",
            "decorations": []
        },
        "armors": [
            {
                "name": "Barrage Piercing",
                "decorations": []
            },
            {
                "name": "Diablos Vest U",
                "decorations": []
            },
            {
                "name": "Diablo Guards U",
                "decorations": []
            },
            {
                "name": "Chrome Metal Coat",
                "decorations": []
            },
            {
                "name": "Chrome Metal Boots",
                "decorations": []
            }
        ],
        "items": [
            {
                "name": "Normal S Lv1",
                "count": "Infinity"
            },
            {
                "name": "Normal S Lv2",
                "count": 50
            },
            {
                "name": "Pierce S Lv1",
                "count": 40
            },
            {
                "name": "Pierce S Lv2",
                "count": 30
            },
            {
                "name": "Pellet S Lv3",
                "count": 30
            },
            {
                "name": "Freeze S",
                "count": 30
            },
            {
                "name": "Mega Potion",
                "count": 5
            },
            {
                "name": "Ration",
                "count": 4
            },
            {
                "name": "Cool Drink",
                "count": 3
            },
            {
                "name": "Sonic Bomb",
                "count": 2
            }
        ]
    },
    {
        "name": "Nargacuga Training",
        "time-limit": 50,
        "location": "GrtForest(Nght)",
        "main-monsters": "Nargacuga",
        "goal-condition": "Hunt the Nargacuga",
        "quest-details": "You win Dual Blades fights by sticking close, so look for openings and stab away! Don't let those chances dance away from you!!",
        "difficulty": 3,
        "point-multiplier": 95,
        "weapon": {
            "name": "Melting Wail+",
            "decorations": []
        },
        "armors": [
            {
                "name": "Diablo Helm U",
                "decorations": [
                    {
                        "name": "Grinder Jewel"
                    }
                ]
            },
            {
                "name": "Hornet Mail S",
                "decorations": [
                    {
                        "name": "Grinder Jewel"
                    }
                ]
            },
            {
                "name": "Hornet Vambraces S",
                "decorations": [
                    {
                        "name": "Grinder Jewel"
                    }
                ]
            },
            {
                "name": "Diablo Coil U",
                "decorations": []
            },
            {
                "name": "Hornet Greaves S",
                "decorations": [
                    {
                        "name": "Grinder Jewel"
                    }
                ]
            }
        ],
        "items": [
            {
                "name": "Whetstone",
                "count": 4
            },
            {
                "name": "Mega Potion",
                "count": 5
            },
            {
                "name": "Ration",
                "count": 2
            },
            {
                "name": "Power Juice",
                "count": 2
            },
            {
                "name": "Shock Trap",
                "count": 1
            },
            {
                "name": "Sonic Bomb",
                "count": 3
            }
        ]
    },
    {
        "name": "Nargacuga Training",
        "time-limit": 50,
        "location": "GrtForest(Nght)",
        "main-monsters": "Nargacuga",
        "goal-condition": "Hunt the Nargacuga",
        "quest-details": "Your chance to deal serious damage lies in when it's charging up! Attack while it's still targeting! And use THAT thing!!",
        "difficulty": 3,
        "point-multiplier": 100,
        "weapon": {
            "name": "Wyvern Blade \"Maple\"",
            "decorations": []
        },
        "armors": [
            {
                "name": "Kirin Piercing",
                "decorations": []
            },
            {
                "name": "Giaprey Mail U",
                "decorations": [
                    {
                        "name": "Dodge Jewel"
                    }
                ]
            },
            {
                "name": "Giaprey Vambraces U",
                "decorations": [
                    {
                        "name": "Dodge Jewel"
                    }
                ]
            },
            {
                "name": "Giaprey Tasset U",
                "decorations": [
                    {
                        "name": "Evade Jewel"
                    }
                ]
            },
            {
                "name": "Giaprey Greaves U",
                "decorations": [
                    {
                        "name": "Dodge Jewel"
                    }
                ]
            }
        ],
        "items": [
            {
                "name": "Whetstone",
                "count": 3
            },
            {
                "name": "Mega Potion",
                "count": 6
            },
            {
                "name": "Ration",
                "count": 4
            },
            {
                "name": "Sply Pitfall Trp",
                "count": 1
            },
            {
                "name": "Sonic Bomb",
                "count": 3
            }
        ]
    },
    {
        "name": "Nargacuga Training",
        "time-limit": 50,
        "location": "GrtForest(Nght)",
        "main-monsters": "Nargacuga",
        "goal-condition": "Hunt the Nargacuga",
        "quest-details": "Your weapon this time is a nice one that can cause Paralysis! Use it to stop the monster and... You know the rest!",
        "difficulty": 3,
        "point-multiplier": 110,
        "weapon": {
            "name": "Devil Masher+",
            "decorations": []
        },
        "armors": [
            {
                "name": "Yellow Piercing",
                "decorations": [
                    {
                        "name": "SpecialAtkJewel"
                    }
                ]
            },
            {
                "name": "Hypno Mail S",
                "decorations": [
                    {
                        "name": "SpecialAtkJewel"
                    }
                ]
            },
            {
                "name": "Gypceros Vambraces S",
                "decorations": [
                    {
                        "name": "SpecialAtkJewel"
                    }
                ]
            },
            {
                "name": "Hypno Tasset S",
                "decorations": []
            },
            {
                "name": "Hypno Greaves S",
                "decorations": [
                    {
                        "name": "SpecialAtkJewel"
                    }
                ]
            }
        ],
        "items": [
            {
                "name": "Whetstone",
                "count": 4
            },
            {
                "name": "Mega Potion",
                "count": 6
            },
            {
                "name": "Ration",
                "count": 4
            },
            {
                "name": "Sply Pitfall Trp",
                "count": 1
            },
            {
                "name": "Sonic Bomb",
                "count": 3
            }
        ]
    },
    {
        "name": "Nargacuga Training",
        "time-limit": 50,
        "location": "GrtForest(Nght)",
        "main-monsters": "Nargacuga",
        "goal-condition": "Hunt the Nargacuga",
        "quest-details": "You're not going to be able to keep up with this bad body with a slow Gunlance. Best to lie in wait, if you know what I mean!",
        "difficulty": 3,
        "point-multiplier": 100,
        "weapon": {
            "name": "Tigrex Gunlance",
            "decorations": []
        },
        "armors": [
            {
                "name": "Ceanataur Helm U",
                "decorations": []
            },
            {
                "name": "Ceanataur Mail U",
                "decorations": []
            },
            {
                "name": "Ceanataur Braces U",
                "decorations": []
            },
            {
                "name": "Ceanataur Tasset U",
                "decorations": []
            },
            {
                "name": "Ceanataur Greaves U",
                "decorations": [
                    {
                        "name": "Strength Jewel"
                    }
                ]
            }
        ],
        "items": [
            {
                "name": "Whetstone",
                "count": 4
            },
            {
                "name": "Mega Potion",
                "count": 5
            },
            {
                "name": "Ration",
                "count": 6
            },
            {
                "name": "Sonic Bomb",
                "count": 3
            }
        ]
    },
    {
        "name": "Nargacuga Training",
        "time-limit": 50,
        "location": "GrtForest(Nght)",
        "main-monsters": "Nargacuga",
        "goal-condition": "Hunt the Nargacuga",
        "quest-details": "Striking and retreating a distance as a tactic isn't going to work against this one. Watch its movements well and react!",
        "difficulty": 3,
        "point-multiplier": 95,
        "weapon": {
            "name": "Fire Wrath",
            "decorations": []
        },
        "armors": [
            {
                "name": "Black Piercing",
                "decorations": []
            },
            {
                "name": "Ceanataur Vest S",
                "decorations": [
                    {
                        "name": "Pierce Jewel"
                    }
                ]
            },
            {
                "name": "Ceanataur Guards U",
                "decorations": [
                    {
                        "name": "Pierce Jewel+"
                    }
                ]
            },
            {
                "name": "Ceanataur Coat U",
                "decorations": [
                    {
                        "name": "Pierce Jewel"
                    }
                ]
            },
            {
                "name": "Ceanataur Leggings S",
                "decorations": []
            }
        ],
        "items": [
            {
                "name": "Normal S Lv1",
                "count": "Infinity"
            },
            {
                "name": "Normal S Lv2",
                "count": 60
            },
            {
                "name": "Pierce S Lv1",
                "count": 15
            },
            {
                "name": "Pierce S Lv2",
                "count": 30
            },
            {
                "name": "Pierce S Lv3",
                "count": 20
            },
            {
                "name": "Flaming S",
                "count": 20
            },
            {
                "name": "Mega Potion",
                "count": 5
            },
            {
                "name": "Ration",
                "count": 4
            },
            {
                "name": "Supply Flash Bmb",
                "count": 1
            }
        ]
    }
]
