[
    {
        "name": "Spiderweb",
        "chances": [
            {
                "level": 0,
                "chance": 15
            },
            {
                "level": 3,
                "chance": 10
            },
            {
                "level": 4,
                "chance": 10
            }
        ]
    },
    {
        "name": "Cricket",
        "chances": [
            {
                "level": 0,
                "chance": 4
            }
        ]
    },
    {
        "name": "Worm",
        "chances": [
            {
                "level": 0,
                "chance": 12
            },
            {
                "level": 1,
                "chance": 7
            }
        ]
    },
    {
        "name": "Firefly",
        "chances": [
            {
                "level": 0,
                "chance": 4
            }
        ]
    },
    {
        "name": "Mega Fishing Fly",
        "chances": [
            {
                "level": 2,
                "chance": 10
            },
            {
                "level": 3,
                "chance": 15
            }
        ]
    },
    {
        "name": "Insect Husk",
        "chances": [
            {
                "level": 0,
                "chance": 4
            }
        ]
    },
    {
        "name": "Yambug",
        "chances": [
            {
                "level": 0,
                "chance": 8
            }
        ]
    },
    {
        "name": "Bughopper",
        "chances": [
            {
                "level": 0,
                "chance": 8
            }
        ]
    },
    {
        "name": "Godbug",
        "chances": [
            {
                "level": 1,
                "chance": 14
            },
            {
                "level": 2,
                "chance": 17
            },
            {
                "level": 3,
                "chance": 6
            },
            {
                "level": 4,
                "chance": 10
            }
        ]
    },
    {
        "name": "Bitterbug",
        "chances": [
            {
                "level": 0,
                "chance": 20
            },
            {
                "level": 1,
                "chance": 15
            },
            {
                "level": 3,
                "chance": 4
            }
        ]
    },
    {
        "name": "Flashbug",
        "chances": [
            {
                "level": 0,
                "chance": 5
            },
            {
                "level": 1,
                "chance": 12
            },
            {
                "level": 3,
                "chance": 7
            },
            {
                "level": 4,
                "chance": 7
            }
        ]
    },
    {
        "name": "Thunderbug",
        "chances": [
            {
                "level": 2,
                "chance": 4
            },
            {
                "level": 3,
                "chance": 10
            }
        ]
    },
    {
        "name": "Carpenterbug",
        "chances": [
            {
                "level": 0,
                "chance": 20
            },
            {
                "level": 0,
                "chance": 24
            }
        ]
    },
    {
        "name": "Killer Beetle",
        "chances": [
            {
                "level": 1,
                "chance": 12
            },
            {
                "level": 2,
                "chance": 25
            }
        ]
    },
    {
        "name": "Hercudrome",
        "chances": [
            {
                "level": 2,
                "chance": 15
            },
            {
                "level": 3,
                "chance": 25
            }
        ]
    },
    {
        "name": "King Scarab",
        "chances": [
            {
                "level": 2,
                "chance": 7
            },
            {
                "level": 3,
                "chance": 15
            },
            {
                "level": 4,
                "chance": 25
            }
        ]
    },
    {
        "name": "Rare Scarab",
        "chances": [
            {
                "level": 3,
                "chance": 5
            },
            {
                "level": 4,
                "chance": 10
            }
        ]
    },
    {
        "name": "Emperor Cricket",
        "chances": [
            {
                "level": 4,
                "chance": 15
            }
        ]
    },
    {
        "name": "PhantomButterfly",
        "chances": [
            {
                "level": 4,
                "chance": 3
            }
        ]
    },
    {
        "name": "Rainbow Insect",
        "chances": [
            {
                "level": 3,
                "chance": 5
            }
        ]
    },
    {
        "name": "Great Hornfly",
        "chances": [
            {
                "level": 1,
                "chance": 4
            },
            {
                "level": 2,
                "chance": 4
            }
        ]
    },
    {
        "name": "Great Ladybug",
        "chances": [
            {
                "level": 1,
                "chance": 4
            },
            {
                "level": 2,
                "chance": 4
            }
        ]
    },
    {
        "name": "Vespoid Shell",
        "chances": [
            {
                "level": 2,
                "chance": 4
            }
        ]
    },
    {
        "name": "Vespoid Carapace",
        "chances": [
            {
                "level": 4,
                "chance": 5
            }
        ]
    },
    {
        "name": "Vespoid Wing",
        "chances": [
            {
                "level": 1,
                "chance": 4
            }
        ]
    },
    {
        "name": "Vespoid InnrWng",
        "chances": [
            {
                "level": 3,
                "chance": 4
            }
        ]
    },
    {
        "name": "Vspoid Razorwing",
        "chances": [
            {
                "level": 4,
                "chance": 5
            }
        ]
    },
    {
        "name": "Hornetaur Shell",
        "chances": [
            {
                "level": 2,
                "chance": 4
            }
        ]
    },
    {
        "name": "Hornetaur Crapce",
        "chances": [
            {
                "level": 4,
                "chance": 5
            }
        ]
    },
    {
        "name": "Hornetaur Wing",
        "chances": [
            {
                "level": 1,
                "chance": 4
            }
        ]
    },
    {
        "name": "HornetaurInnrWng",
        "chances": [
            {
                "level": 3,
                "chance": 4
            }
        ]
    },
    {
        "name": "Hornet Razorwing",
        "chances": [
            {
                "level": 4,
                "chance": 5
            }
        ]
    }
]
