[
    {
        "id": 0,
        "upgrade": "Field Row+1",
        "pt-cost": 1000
    },
    {
        "id": 1,
        "upgrade": "Field Row+2",
        "pt-cost": 1500
    },
    {
        "id": 2,
        "upgrade": "Fishing Pier+1",
        "pt-cost": 2000
    },
    {
        "id": 3,
        "upgrade": "Fishing Pier+2",
        "pt-cost": 4000
    },
    {
        "id": 4,
        "upgrade": "Casting Machine",
        "pt-cost": 6000
    },
    {
        "id": 5,
        "upgrade": "Mining Point+1",
        "pt-cost": 4000
    },
    {
        "id": 6,
        "upgrade": "Mining Point+2",
        "pt-cost": 6000
    },
    {
        "id": 7,
        "upgrade": "Mining Point+3",
        "pt-cost": 8000
    },
    {
        "id": 8,
        "upgrade": "Mining Point+4",
        "pt-cost": 10000
    },
    {
        "id": 9,
        "upgrade": "Mining Bomb",
        "pt-cost": 6000
    },
    {
        "id": 10,
        "upgrade": "Insect Thicket+1",
        "pt-cost": 3000
    },
    {
        "id": 11,
        "upgrade": "Insect Thicket+2",
        "pt-cost": 5000
    },
    {
        "id": 12,
        "upgrade": "Insect Thicket+3",
        "pt-cost": 7000
    },
    {
        "id": 13,
        "upgrade": "Insect Thicket+4",
        "pt-cost": 9000
    },
    {
        "id": 14,
        "upgrade": "Bug Tree",
        "pt-cost": 6000
    },
    {
        "id": 15,
        "upgrade": "Mushroom Tree",
        "pt-cost": 1000
    },
    {
        "id": 16,
        "upgrade": "Mushroom Tree+1",
        "pt-cost": 2500
    },
    {
        "id": 17,
        "upgrade": "Mushroom Tree+2",
        "pt-cost": 4000
    },
    {
        "id": 18,
        "upgrade": "PrototypeBeeHive",
        "pt-cost": 1000
    },
    {
        "id": 19,
        "upgrade": "ProductionBeeHive",
        "pt-cost": 3000
    },
    {
        "id": 20,
        "upgrade": "Modified BeeHive",
        "pt-cost": 5000
    },
    {
        "id": 21,
        "upgrade": "Trenya's Boat",
        "pt-cost": 500
    }
]